dspp_reader/__init__.py
dspp_reader/version.py
dspp_reader/sqmle/__init__.py
dspp_reader/sqmle/scripts.py
dspp_reader/sqmle/sqmle.py
dspp_reader/sqmle/tests/__init__.py
dspp_reader/tessw4c/__init__.py
dspp_reader/tessw4c/scripts.py
dspp_reader/tessw4c/tessw4c.py
dspp_reader/tessw4c/tests/__init__.py
dspp_reader/tools/__init__.py
dspp_reader/tools/common.py
dspp_reader/tools/device.py
dspp_reader/tools/generics.py
dspp_reader/tools/site.py
dspp_reader/tools/tests/__init__.py
dspp_reader/tools/tests/test_device.py
dspp_reader/tools/tests/test_generics.py
dspp_reader/tools/tests/test_site.py
dspp_reader-0.3.0.dist-info/licenses/LICENSE
dspp_reader-0.3.0.dist-info/METADATA
dspp_reader-0.3.0.dist-info/WHEEL
dspp_reader-0.3.0.dist-info/entry_points.txt
dspp_reader-0.3.0.dist-info/top_level.txt
dspp_reader-0.3.0.dist-info/RECORD
