Metadata-Version: 2.4
Name: dspp_reader
Version: 0.3.0
Summary: Software for reading SQMs and TESS-W4C devices, used for measuring sky brightness.
Author-email: Simón Torres <simon.torres@noirlab.edu>, Guillermo Damke <guillermo.damke@noirlab.edu>
Maintainer-email: Simón Torres <simon.torres@noirlab.edu>
License-Expression: BSD-3-Clause
Project-URL: Homepage, https://dspp-reader.readthedocs.io/en/latest/
Project-URL: Bug Reports, https://github.com/dark-sky-protection/dspp_reader/issues
Project-URL: Source, https://github.com/dark-sky-protection/dspp_reader
Keywords: sqm,sqm-le,tess-4c,sky,darkness,astronomy
Classifier: Development Status :: 2 - Pre-Alpha
Classifier: Environment :: Console
Classifier: Intended Audience :: Developers
Classifier: Intended Audience :: Education
Classifier: Intended Audience :: Science/Research
Classifier: Programming Language :: Python :: 3.14
Classifier: Natural Language :: English
Classifier: Operating System :: POSIX :: Linux
Classifier: Operating System :: POSIX :: Other
Classifier: Operating System :: MacOS :: MacOS X
Classifier: Topic :: Scientific/Engineering :: Astronomy
Classifier: Topic :: Software Development :: Libraries :: Python Modules
Requires-Python: >=3.13
License-File: LICENSE
Requires-Dist: astropy
Requires-Dist: astroplan
Requires-Dist: packaging
Requires-Dist: requests
Requires-Dist: sphinx
Requires-Dist: sphinxcontrib-napoleon
Requires-Dist: pandas
Requires-Dist: pydata-sphinx-theme
Requires-Dist: pyyaml
Requires-Dist: tzlocal
Dynamic: license-file
